{"id":"9c3786df-e539-493b-b3eb-034e5dc95d01","hw_part":{"name":"MHT04"},"placement":{"id":"e1a0206d-c1a8-4d8b-867a-6a4dcecbd51e","display_name":"15 - 16 106 wc","name":"106 wc","number":15,"tags":[{"id":"83fdc98d-f722-4e26-ba19-a48721fdec56","name":"Construction of building"},{"id":"62a94dfb-3dbc-4fc7-b0f4-610b6c5f19af","name":"Wc"}],"positions":[{"id":"920a8483-f87d-4aee-a576-996a29906992","positionable_type":"Floorplan","positionable_id":"21fcce23-1d86-4c13-90a7-2dc5d9154728","pos_x":"0.568643593","pos_y":"0.65611799","is_primary":true,"created_at":"2025-07-22T15:35:34.622+0000","updated_at":"2025-07-22T15:35:34.622+0000"}],"created_at":"2023-01-23T13:30:22.799+0000","updated_at":"2024-06-18T19:00:29.799+0000"},"product":{"id":"095ab501-060c-403b-863d-a6598f3e8b8a","name":"MHT","product_type":{"id":"84bcdf36-961d-44a6-87f3-234ac37f528c","name":"Sensor"}},"address":16,"activated_at":"2024-04-04T08:27:57.056+0000","created_at":"2023-01-23T13:30:23.037+0000","disabled_at":null,"updated_at":"2024-04-04T08:27:57.303+0000"}
