{"id":"4570de5f-4537-486b-817b-2e32dfd4f4da","hw_part":{"name":"HT02"},"placement":{"id":"813b5586-914a-456e-8b5d-306779d7397a","display_name":"7 - 4 102 koupelna (sprcha, wc)","name":"102 koupelna (sprcha, wc)","number":7,"tags":[{"id":"83fdc98d-f722-4e26-ba19-a48721fdec56","name":"Construction of building"}],"positions":[{"id":"d64f3cfd-bd7d-4491-8506-05e85c2fcf6d","positionable_type":"Floorplan","positionable_id":"e8fe5735-d1f7-4ac0-8ee3-6becd84ae487","pos_x":"0.334204268","pos_y":"0.52089636","is_primary":true,"created_at":"2025-07-22T15:19:46.862+0000","updated_at":"2025-07-22T15:19:46.862+0000"}],"created_at":"2021-05-07T14:31:41.964+0000","updated_at":"2024-01-16T13:17:00.629+0000"},"product":{"id":"d7915551-3a61-4621-9b76-ca36dd790f9b","name":"HT","product_type":{"id":"84bcdf36-961d-44a6-87f3-234ac37f528c","name":"Sensor"}},"address":4,"activated_at":"2024-01-10T13:34:56.753+0000","created_at":"2021-05-07T14:31:42.062+0000","disabled_at":null,"updated_at":"2024-01-10T13:34:56.981+0000"}
